proman/common/__init__.py
proman/common/config.py
proman/common/dependencies.py
proman/common/exception.py
proman/common/filepaths.py
proman/common/manifest.py
proman/common/packaging_bases.py
proman/common/system.py
proman/py.typed
proman/vcs/__init__.py
proman/vcs/git/__init__.py
proman/vcs/git/_vendor/LICENSE
proman/vcs/git/_vendor/gitignore/.github/PULL_REQUEST_TEMPLATE.md
proman/vcs/git/_vendor/gitignore/.travis.yml
proman/vcs/git/_vendor/gitignore/Actionscript.gitignore
proman/vcs/git/_vendor/gitignore/Ada.gitignore
proman/vcs/git/_vendor/gitignore/Agda.gitignore
proman/vcs/git/_vendor/gitignore/Android.gitignore
proman/vcs/git/_vendor/gitignore/AppEngine.gitignore
proman/vcs/git/_vendor/gitignore/AppceleratorTitanium.gitignore
proman/vcs/git/_vendor/gitignore/ArchLinuxPackages.gitignore
proman/vcs/git/_vendor/gitignore/Autotools.gitignore
proman/vcs/git/_vendor/gitignore/C++.gitignore
proman/vcs/git/_vendor/gitignore/C.gitignore
proman/vcs/git/_vendor/gitignore/CFWheels.gitignore
proman/vcs/git/_vendor/gitignore/CMake.gitignore
proman/vcs/git/_vendor/gitignore/CONTRIBUTING.md
proman/vcs/git/_vendor/gitignore/CUDA.gitignore
proman/vcs/git/_vendor/gitignore/CakePHP.gitignore
proman/vcs/git/_vendor/gitignore/ChefCookbook.gitignore
proman/vcs/git/_vendor/gitignore/CodeIgniter.gitignore
proman/vcs/git/_vendor/gitignore/CommonLisp.gitignore
proman/vcs/git/_vendor/gitignore/Composer.gitignore
proman/vcs/git/_vendor/gitignore/Concrete5.gitignore
proman/vcs/git/_vendor/gitignore/Coq.gitignore
proman/vcs/git/_vendor/gitignore/CraftCMS.gitignore
proman/vcs/git/_vendor/gitignore/D.gitignore
proman/vcs/git/_vendor/gitignore/DM.gitignore
proman/vcs/git/_vendor/gitignore/Dart.gitignore
proman/vcs/git/_vendor/gitignore/Delphi.gitignore
proman/vcs/git/_vendor/gitignore/Drupal.gitignore
proman/vcs/git/_vendor/gitignore/EPiServer.gitignore
proman/vcs/git/_vendor/gitignore/Eagle.gitignore
proman/vcs/git/_vendor/gitignore/Elisp.gitignore
proman_common-0.1.1a6.dist-info/LICENSE.md
proman_common-0.1.1a6.dist-info/WHEEL
proman_common-0.1.1a6.dist-info/METADATA
proman_common-0.1.1a6.dist-info/RECORD
